simple_toml_settings/__init__.py
simple_toml_settings/exceptions.py
simple_toml_settings/py.typed
simple_toml_settings/settings.py
simple_toml_settings/xdg_config.py
simple_toml_settings-0.10.0.dist-info/WHEEL
simple_toml_settings-0.10.0.dist-info/METADATA
simple_toml_settings-0.10.0.dist-info/RECORD
