Metadata-Version: 2.4
Name: simple-toml-settings
Version: 0.10.0
Summary: A Python library to save your settings in a TOML file.
Author: Grant Ramsay
Author-email: Grant Ramsay <grant@gnramsay.com>
License-Expression: MIT
Classifier: Development Status :: 4 - Beta
Classifier: Intended Audience :: Developers
Classifier: License :: OSI Approved :: MIT License
Classifier: Operating System :: OS Independent
Classifier: Programming Language :: Python :: 3
Classifier: Programming Language :: Python :: 3.9
Classifier: Programming Language :: Python :: 3.10
Classifier: Programming Language :: Python :: 3.11
Classifier: Programming Language :: Python :: 3.12
Classifier: Programming Language :: Python :: 3.13
Classifier: Programming Language :: Python :: 3.14
Classifier: Topic :: Software Development :: Libraries :: Python Modules
Requires-Dist: rtoml>=0.12.0
Requires-Python: >=3.9
Project-URL: Homepage, http://toml-settings.grantramsay.dev/
Project-URL: Pull Requests, https://github.com/seapagan/simple-toml-settings/pulls
Project-URL: Bug Tracker, https://github.com/seapagan/simple-toml-settings/issues
Project-URL: Changelog, https://github.com/seapagan/simple-toml-settings/blob/main/CHANGELOG.md
Project-URL: Repository, https://github.com/seapagan/simple-toml-settings
